src/do-ddns/__init__.py
src/do-ddns/ddns.py
do_ddns-0.3.1.dist-info/METADATA
do_ddns-0.3.1.dist-info/WHEEL
do_ddns-0.3.1.dist-info/licenses/LICENSE
do_ddns-0.3.1.dist-info/RECORD
