Metadata-Version: 2.1
Name: do-ddns
Version: 0.3.1
Summary: A dynamic DNS soultion for Digital Ocean useres
Project-URL: Homepage, https://gitlab.pm/rune/ddns
Project-URL: Bug Tracker, https://gitlab.pm/rune/ddns/issues
Author-email: Rune <pypi@rune.pm>
License-Expression: GPL-3.0-or-later
License-File: LICENSE
Classifier: Development Status :: 4 - Beta
Classifier: License :: OSI Approved :: GNU General Public License v3 or later (GPLv3+)
Classifier: Operating System :: OS Independent
Classifier: Programming Language :: Python :: 3
Requires-Python: >=3.7
Requires-Dist: requests==2.28.2
Requires-Dist: rich==13.3.2
